README.rst
setup.py
utilkit/__init__.py
utilkit/datetimeutil.py
utilkit/fileutil.py
utilkit/printutil.py
utilkit/stringutil.py
utilkit/versionutil.py
utilkit.egg-info/PKG-INFO
utilkit.egg-info/SOURCES.txt
utilkit.egg-info/dependency_links.txt
utilkit.egg-info/requires.txt
utilkit.egg-info/top_level.txt
utilkit.egg-info/zip-safe